neurosym
tests
tutorial
