Metadata-Version: 2.4
Name: neurosym
Version: 0.0.74
Summary: Neurosymbolic library.
Home-page: https://github.com/kavigupta/neurosym-lib
Author: Kavi Gupta, Atharva Sehgal, Maddy Bowers, Armando Solar-Lezama
Author-email: kavig+neurosym@mit.edu
Classifier: Programming Language :: Python :: 3.10
Classifier: Programming Language :: Python :: 3.11
Classifier: Programming Language :: Python :: 3.12
Classifier: Operating System :: OS Independent
Requires-Python: >=3.10
Requires-Dist: frozendict==2.3.8
Requires-Dist: torch
Requires-Dist: torchvision
Requires-Dist: torchaudio
Requires-Dist: numpy
Requires-Dist: pytorch-lightning
Requires-Dist: permacache
Requires-Dist: requests
Requires-Dist: stitch-core==0.1.25
Requires-Dist: scikit-learn
Requires-Dist: s-exp-parser==1.4.0
Requires-Dist: no_toplevel_code==1.0.0
Requires-Dist: ast-scope==0.5.2
Requires-Dist: pathos==0.3.2
Dynamic: author-email
Dynamic: classifier
Dynamic: description
Dynamic: description-content-type
Dynamic: home-page
Dynamic: requires-dist
Dynamic: requires-python
Dynamic: summary
